paramspy/__init__.py
paramspy/cli.py
paramspy/core/fetcher.py
paramspy/core/json_cache.py
paramspy/core/parser.py
paramspy/data/builtin_params.json
paramspy/data/gf_mappings.yaml
paramspy/utils/output.py
hsignal_paramspy-0.1.0.dist-info/METADATA
hsignal_paramspy-0.1.0.dist-info/WHEEL
hsignal_paramspy-0.1.0.dist-info/entry_points.txt
hsignal_paramspy-0.1.0.dist-info/licenses/LICENSE
hsignal_paramspy-0.1.0.dist-info/RECORD
