Metadata-Version: 2.4
Name: hsignal-paramspy
Version: 0.1.0
Summary: The high-signal parameter discovery tool. Finds target-specific, production-used parameters from 10+ years of Wayback data.
Project-URL: Homepage, https://github.com/MenukaRisith/paramspy
Project-URL: Documentation, https://github.com/MenukaRisith/paramspy
Project-URL: Source, https://github.com/MenukaRisith/paramspy
Author-email: Menuka Risith <menuka.contact@gmail.com>
License: MIT License
License-File: LICENSE
Keywords: bug-bounty,hacking,parameter-discovery,recon,security
Classifier: Intended Audience :: Developers
Classifier: License :: OSI Approved :: MIT License
Classifier: Operating System :: OS Independent
Classifier: Programming Language :: Python :: 3
Classifier: Topic :: Security
Requires-Python: >=3.9
Requires-Dist: httpx>=0.27.0
Requires-Dist: pydantic>=2.6.1
Requires-Dist: python-dotenv>=1.0.1
Requires-Dist: pyyaml>=6.0.1
Requires-Dist: sqlite-utils>=3.35.0
Requires-Dist: typer[all]>=0.12.3
Requires-Dist: urllib3>=2.2.1
